lnpanda/__init__.py
lnpanda/__main.__py
lnpanda/lnpanda.py
lnpanda-0.2.4.dist-info/entry_points.txt
lnpanda-0.2.4.dist-info/WHEEL
lnpanda-0.2.4.dist-info/METADATA
lnpanda-0.2.4.dist-info/RECORD
