Metadata-Version: 2.1
Name: lnpanda
Version: 0.2.4
Summary: A tool which pairs Pandas to LND Lightning Network Data for Data Science
License: MIT
Author: Sam Korn
Author-email: korn94sam@gmail.com
Requires-Python: >=3.8
Classifier: License :: OSI Approved :: MIT License
Classifier: Programming Language :: Python :: 3
Classifier: Programming Language :: Python :: 3.10
Classifier: Programming Language :: Python :: 3.8
Classifier: Programming Language :: Python :: 3.9
Requires-Dist: lnd-grpc-client (==0.5.0)
Requires-Dist: loop-grpc-client (>=0.1.3,<0.2.0)
Requires-Dist: pandas (>=1.2.4,<2.0.0)
Requires-Dist: pdir2 (>=0.3.2,<0.4.0)
Requires-Dist: pool-grpc-client (>=0.1.0,<0.2.0)
Requires-Dist: protobuf3-to-dict (>=0.1.5,<0.2.0)
